stackit/rabbitmq/__init__.py
stackit/rabbitmq/api/__init__.py
stackit/rabbitmq/api/default_api.py
stackit/rabbitmq/api_client.py
stackit/rabbitmq/api_response.py
stackit/rabbitmq/configuration.py
stackit/rabbitmq/exceptions.py
stackit/rabbitmq/models/__init__.py
stackit/rabbitmq/models/backup.py
stackit/rabbitmq/models/create_backup_response_item.py
stackit/rabbitmq/models/create_instance_payload.py
stackit/rabbitmq/models/create_instance_response.py
stackit/rabbitmq/models/credentials.py
stackit/rabbitmq/models/credentials_list_item.py
stackit/rabbitmq/models/credentials_response.py
stackit/rabbitmq/models/error.py
stackit/rabbitmq/models/get_metrics_response.py
stackit/rabbitmq/models/instance.py
stackit/rabbitmq/models/instance_last_operation.py
stackit/rabbitmq/models/instance_parameters.py
stackit/rabbitmq/models/instance_schema.py
stackit/rabbitmq/models/list_backups_response.py
stackit/rabbitmq/models/list_credentials_response.py
stackit/rabbitmq/models/list_instances_response.py
stackit/rabbitmq/models/list_offerings_response.py
stackit/rabbitmq/models/list_restores_response.py
stackit/rabbitmq/models/model_schema.py
stackit/rabbitmq/models/offering.py
stackit/rabbitmq/models/partial_update_instance_payload.py
stackit/rabbitmq/models/plan.py
stackit/rabbitmq/models/raw_credentials.py
stackit/rabbitmq/models/restore.py
stackit/rabbitmq/models/trigger_restore_response.py
stackit/rabbitmq/models/update_backups_config_payload.py
stackit/rabbitmq/models/update_backups_config_response.py
stackit/rabbitmq/py.typed
stackit/rabbitmq/rest.py
stackit_rabbitmq-0.3.0.dist-info/LICENSE.md
stackit_rabbitmq-0.3.0.dist-info/METADATA
stackit_rabbitmq-0.3.0.dist-info/NOTICE.txt
stackit_rabbitmq-0.3.0.dist-info/WHEEL
stackit_rabbitmq-0.3.0.dist-info/RECORD
